{"cameraMode":{"drawMode":0,"name":"Shaded","section":"Shading Mode"},"sceneLighting":false,"audioPlay":false,"sceneViewState":{"showFog":true,"showMaterialUpdate":false,"showSkybox":false,"showFlares":true,"showImageEffects":true,"showParticleSystems":true},"in2DMode":false,"pivot":{"x":-0.37999987602233889,"y":3.362212657928467,"z":2.069999933242798},"rotation":{"x":-0.027746059000492097,"y":-0.35493457317352297,"z":-0.010555512271821499,"w":0.9344401359558106},"size":20.932357788085939,"orthographic":false}